<!-- This is a generated file. It is highly recommended that you DO NOT edit this file. --><iq:manifest xmlns:iq="http://www.garmin.com/xml/connectiq" version="3">
    <iq:application entry="GarminTrexGameApp" id="df081c367a2e4e839fb3a423a343e842" launcherIcon="@Drawables.LauncherIcon" minSdkVersion="1.2.0" name="@Strings.AppName" type="watch-app" version="0.0.0">
        <iq:products>
            <iq:product id="fr945"/>
            <iq:product id="vivoactive"/>
        </iq:products>
        <iq:permissions/>
        <iq:languages>
            <iq:language>eng</iq:language>
        </iq:languages>
        <iq:barrels/>
    </iq:application>
</iq:manifest>
